README.md
setup.py
benepar/__init__.py
benepar/base_parser.py
benepar/bert_tokenization.py
benepar/chart_decoder.c
benepar/chart_decoder.pyx
benepar/downloader.py
benepar/nltk_plugin.py
benepar/spacy_plugin.py
benepar.egg-info/PKG-INFO
benepar.egg-info/SOURCES.txt
benepar.egg-info/dependency_links.txt
benepar.egg-info/requires.txt
benepar.egg-info/top_level.txt