Metadata-Version: 2.1
Name: benepar
Version: 0.1.3
Summary: Berkeley Neural Parser
Home-page: https://github.com/nikitakit/self-attentive-parser
Author: Nikita Kitaev
Author-email: kitaev@cs.berkeley.edu
License: UNKNOWN
Platform: UNKNOWN
Classifier: Programming Language :: Python :: 2.7
Classifier: Programming Language :: Python :: 3
Classifier: License :: OSI Approved :: Apache Software License
Classifier: Operating System :: OS Independent
Classifier: Topic :: Scientific/Engineering :: Artificial Intelligence
Classifier: Topic :: Text Processing :: Linguistic
Provides-Extra: cpu
Provides-Extra: gpu
Provides-Extra: spacy
